bach_baidu_maps-1.0.2.dist-info/licenses/LICENSE
mcp_server_baidu_maps/__init__.py
mcp_server_baidu_maps/__main__.py
mcp_server_baidu_maps/map.py
bach_baidu_maps-1.0.2.dist-info/METADATA
bach_baidu_maps-1.0.2.dist-info/WHEEL
bach_baidu_maps-1.0.2.dist-info/entry_points.txt
bach_baidu_maps-1.0.2.dist-info/top_level.txt
bach_baidu_maps-1.0.2.dist-info/RECORD
