Metadata-Version: 2.4
Name: bach-baidu-maps
Version: 1.0.2
Summary: MCP Server Baidu Maps Enhanced - HTTP call Baidu Map API for MCP
Author-email: bachstudio <bachstudio@example.com>
License: MIT
Project-URL: Homepage, https://github.com/BACH-AI-Tools/baidu-maps-mcp
Project-URL: Repository, https://github.com/BACH-AI-Tools/baidu-maps-mcp
Project-URL: Bug Reports, https://github.com/BACH-AI-Tools/baidu-maps-mcp/issues
Keywords: mcp,map,baidu,baidu-maps,fastmcp,http
Requires-Python: >=3.11
License-File: LICENSE
Requires-Dist: mcp[cli]>=1.9.0
Requires-Dist: httpx>=0.27.0
Dynamic: license-file
